{
  "fileName": "camp-editions.csv",
  "separator": ",",
  "encoding": "UTF-8",
  "columns": [
    {
      "name": "campName",
      "type": "string",
      "required": true,
      "references": "camps.csv:name",
      "notes": "Must match an existing Camp.Name in the DB. Case-insensitive lookup."
    },
    {
      "name": "year",
      "type": "integer",
      "required": true,
      "notes": "Parsed with int.Parse(). API validator restricts 2000-2100 but importer has no range check.",
      "confidence": "low"
    },
    {
      "name": "startDate",
      "type": "date",
      "required": true,
      "notes": "Parsed with DateTime.Parse(). ISO 8601 format recommended (yyyy-MM-dd or yyyy-MM-ddTHH:mm:ss).",
      "confidence": "low"
    },
    {
      "name": "endDate",
      "type": "date",
      "required": true,
      "notes": "Parsed with DateTime.Parse(). API validator enforces endDate > startDate but importer does NOT.",
      "confidence": "low"
    },
    {
      "name": "pricePerAdult",
      "type": "decimal",
      "required": true,
      "format": "^\\d+(\\.\\d{1,2})?$",
      "notes": "decimal.Parse(InvariantCulture). DB constraint: >= 0, precision(10,2)."
    },
    {
      "name": "pricePerChild",
      "type": "decimal",
      "required": true,
      "format": "^\\d+(\\.\\d{1,2})?$"
    },
    {
      "name": "pricePerBaby",
      "type": "decimal",
      "required": true,
      "format": "^\\d+(\\.\\d{1,2})?$"
    },
    {
      "name": "maxCapacity",
      "type": "integer",
      "required": false,
      "notes": "Parsed with int.Parse() if present."
    },
    {
      "name": "status",
      "type": "string",
      "required": true,
      "allowedValues": ["Proposed", "Draft", "Open", "Closed", "Completed"],
      "notes": "Enum.Parse with ignoreCase:true. Stored as varchar(20)."
    },
    {
      "name": "notes",
      "type": "string",
      "required": false,
      "maxLength": 2000
    }
  ],
  "constraints": {
    "uniqueColumns": [["campName", "year"]],
    "dependsOn": ["camps.csv"],
    "notes": "Composite uniqueness: (campId, year). campName is resolved to campId. DB has composite index IX_CampEditions_CampId_Year."
  }
}
